pdgogogo/__init__.py
pdgogogo/core.py
pdgogogo-0.1.1.dist-info/METADATA
pdgogogo-0.1.1.dist-info/WHEEL
pdgogogo-0.1.1.dist-info/licenses/LICENSE
pdgogogo-0.1.1.dist-info/RECORD
