Metadata-Version: 2.4
Name: pdgogogo
Version: 0.1.1
Summary: A package for testing
Author-email: Keyork <chengky18@icloud.com>
License-File: LICENSE
Requires-Python: >=3.10
Requires-Dist: matplotlib>=3.4.0
Requires-Dist: numpy>=1.20.0
Requires-Dist: pandas>=1.3.0
Requires-Dist: scikit-learn>=0.24.0
Requires-Dist: scipy>=1.7.0
Requires-Dist: seaborn>=0.11.0
